pyweet/__init__.py
pyweet/base.py
pyweet/colors.py
pyweet/oauth.py
pyweet/settings.py
pyweet/spam.py
pyweet/wraps.py
pyweet-0.0.6.data/scripts/pyweet
pyweet-0.0.6.dist-info/DESCRIPTION.rst
pyweet-0.0.6.dist-info/METADATA
pyweet-0.0.6.dist-info/RECORD
pyweet-0.0.6.dist-info/WHEEL
pyweet-0.0.6.dist-info/metadata.json
pyweet-0.0.6.dist-info/top_level.txt
