Metadata-Version: 2.0
Name: pyweet
Version: 0.0.6
Summary: Twitter command line util
Home-page: https://github.com/a-tal/pyweet
Author: Adam Talsma
Author-email: adam@talsma.ca
License: BSD
Download-URL: https://github.com/a-tal/pyweet
Platform: UNKNOWN
Classifier: Development Status :: 5 - Production/Stable
Classifier: Environment :: Console
Classifier: Intended Audience :: System Administrators
Classifier: License :: OSI Approved :: BSD License
Classifier: Operating System :: POSIX :: Linux
Classifier: Programming Language :: Python
Requires-Dist: blessings
Requires-Dist: twitter
